zen_temple/__init__.py
zen_temple/config.py
zen_temple/errors.py
zen_temple/main.py
zen_temple/py.typed
zen_temple/versions.py
zen_temple/controllers/__init__.py
zen_temple/controllers/solution_controller.py
zen_temple/explorer/apple-touch-icon.png
zen_temple/explorer/favicon-96x96.png
zen_temple/explorer/favicon.ico
zen_temple/explorer/favicon.svg
zen_temple/explorer/index.html
zen_temple/explorer/logo.png
zen_temple/explorer/site.webmanifest
zen_temple/explorer/web-app-manifest-192x192.png
zen_temple/explorer/web-app-manifest-512x512.png
zen_temple/explorer/zen_garden_700x700.png
zen_temple/explorer/_app/env.js
zen_temple/explorer/_app/version.json
zen_temple/explorer/_app/immutable/assets/0.De4ew3KS.css
zen_temple/explorer/_app/immutable/assets/6.CYef66zj.css
zen_temple/explorer/_app/immutable/assets/bootstrap-icons.BeopsB42.woff
zen_temple/explorer/_app/immutable/assets/bootstrap-icons.mSm7cUeB.woff2
zen_temple/explorer/_app/immutable/chunks/43hnhKVC.js
zen_temple/explorer/_app/immutable/chunks/B0JcWw2B.js
zen_temple/explorer/_app/immutable/chunks/B0yRDBcJ.js
zen_temple/explorer/_app/immutable/chunks/B34HR-o6.js
zen_temple/explorer/_app/immutable/chunks/B5O290y9.js
zen_temple/explorer/_app/immutable/chunks/BGj-pI5n.js
zen_temple/explorer/_app/immutable/chunks/BHsOWwkz.js
zen_temple/explorer/_app/immutable/chunks/BMW1TMf0.js
zen_temple/explorer/_app/immutable/chunks/BP8Gc9yF.js
zen_temple/explorer/_app/immutable/chunks/BXl3LOEh.js
zen_temple/explorer/_app/immutable/chunks/Btt3Sv-I.js
zen_temple/explorer/_app/immutable/chunks/CBu3SFCv.js
zen_temple/explorer/_app/immutable/chunks/CKVG5F6U.js
zen_temple/explorer/_app/immutable/chunks/Cg8MRuhV.js
zen_temple/explorer/_app/immutable/chunks/CgsLtv0Y.js
zen_temple/explorer/_app/immutable/chunks/CmltHaS5.js
zen_temple/explorer/_app/immutable/chunks/CpFZsRVk.js
zen_temple/explorer/_app/immutable/chunks/CrYqV5xP.js
zen_temple/explorer/_app/immutable/chunks/CtfZr6x0.js
zen_temple/explorer/_app/immutable/chunks/CuNXTB5A.js
zen_temple-0.9.1.dist-info/licenses/LICENSE
zen_temple-0.9.1.dist-info/METADATA
zen_temple-0.9.1.dist-info/WHEEL
zen_temple-0.9.1.dist-info/top_level.txt
zen_temple-0.9.1.dist-info/RECORD
