Metadata-Version: 2.4
Name: zen_temple
Version: 0.9.1
Summary: The visualization plattform for ZEN-garden
Author-email: ZEN-garden developers <zen-garden@ethz.ch>
Project-URL: Homepage, https://github.com/ZEN-universe/ZEN-temple
Project-URL: Issues, https://github.com/ZEN-universe/ZEN-temple/issues
Classifier: Programming Language :: Python :: 3
Classifier: License :: OSI Approved :: MIT License
Classifier: Operating System :: OS Independent
Requires-Python: >=3.10
License-File: LICENSE
Requires-Dist: uvicorn
Requires-Dist: fastapi[standard]
Requires-Dist: python-dotenv
Requires-Dist: zen-garden>=2.8.6
Requires-Dist: mypy>=1.14.1
Provides-Extra: mypy
Requires-Dist: pandas-stubs; extra == "mypy"
Dynamic: license-file
